ansys/rocky/core/__init__.py
ansys/rocky/core/client.py
ansys/rocky/core/examples.py
ansys/rocky/core/exceptions.py
ansys/rocky/core/launcher.py
ansys/rocky/core/rocky_api_proxies.py
ansys/rocky/core/serializers.py
ansys/rocky/core/_api_stubs/plugins10/plugins/api/api_element_item.pyi
ansys/rocky/core/_api_stubs/rocky30/plugins/api/__init__.pyi
ansys/rocky/core/_api_stubs/rocky30/plugins/api/_ra_orientation_mixin.pyi
ansys/rocky/core/_api_stubs/rocky30/plugins/api/_ra_subject_with_coloring_mixin.pyi
ansys/rocky/core/_api_stubs/rocky30/plugins/api/ra_addin_list.pyi
ansys/rocky/core/_api_stubs/rocky30/plugins/api/ra_addin_process.pyi
ansys/rocky/core/_api_stubs/rocky30/plugins/api/ra_addins.pyi
ansys/rocky/core/_api_stubs/rocky30/plugins/api/ra_additional_features.pyi
ansys/rocky/core/_api_stubs/rocky30/plugins/api/ra_airflow.pyi
ansys/rocky/core/_api_stubs/rocky30/plugins/api/ra_api.pyi
ansys/rocky/core/_api_stubs/rocky30/plugins/api/ra_base_geometry.pyi
ansys/rocky/core/_api_stubs/rocky30/plugins/api/ra_base_subject_element.pyi
ansys/rocky/core/_api_stubs/rocky30/plugins/api/ra_base_tagging.pyi
ansys/rocky/core/_api_stubs/rocky30/plugins/api/ra_calculations.pyi
ansys/rocky/core/_api_stubs/rocky30/plugins/api/ra_cfd_coupling.pyi
ansys/rocky/core/_api_stubs/rocky30/plugins/api/ra_cfd_parameters.pyi
ansys/rocky/core/_api_stubs/rocky30/plugins/api/ra_circular_surface.pyi
ansys/rocky/core/_api_stubs/rocky30/plugins/api/ra_contact_data.pyi
ansys/rocky/core/_api_stubs/rocky30/plugins/api/ra_contact_to_particle_process.pyi
ansys/rocky/core/_api_stubs/rocky30/plugins/api/ra_contacts_data_mesh_coloring.pyi
ansys/rocky/core/_api_stubs/rocky30/plugins/api/ra_coupled_wall.pyi
ansys/rocky/core/_api_stubs/rocky30/plugins/api/ra_custom_calculators.pyi
ansys/rocky/core/_api_stubs/rocky30/plugins/api/ra_custom_input.pyi
ansys/rocky/core/_api_stubs/rocky30/plugins/api/ra_divisions_tagging.pyi
ansys/rocky/core/_api_stubs/rocky30/plugins/api/ra_domain_settings.pyi
ansys_rocky_core-0.4.0.dist-info/licenses/LICENSE
ansys_rocky_core-0.4.0.dist-info/WHEEL
ansys_rocky_core-0.4.0.dist-info/METADATA
ansys_rocky_core-0.4.0.dist-info/RECORD
