Metadata-Version: 2.4
Name: ansys-rocky-core
Version: 0.4.0
Summary: Python client library for Ansys Rocky
Author-email: "ANSYS, Inc." <pyansys.core@ansys.com>
Requires-Python: >=3.10,<4
Classifier: Development Status :: 4 - Beta
Classifier: Intended Audience :: Science/Research
Classifier: Topic :: Scientific/Engineering :: Information Analysis
Classifier: License :: OSI Approved :: MIT License
Classifier: Operating System :: OS Independent
Classifier: Programming Language :: Python :: 3.10
Classifier: Programming Language :: Python :: 3.11
Classifier: Programming Language :: Python :: 3.12
Classifier: Programming Language :: Python :: 3.13
License-File: LICENSE
Requires-Dist: importlib-metadata>=4.0
Requires-Dist: Pyro5>=5.13
Requires-Dist: numpy>=1.19, <3.0
Requires-Dist: ansys-tools-common>=0.3.1
Requires-Dist: click==8.3.1
Requires-Dist: ansys-sphinx-theme[autoapi]==1.6.3 ; extra == "doc"
Requires-Dist: numpydoc==1.9.0 ; extra == "doc"
Requires-Dist: Sphinx==8.2.3 ; extra == "doc"
Requires-Dist: sphinx-copybutton==0.5.2 ; extra == "doc"
Requires-Dist: sphinx-gallery==0.19.0 ; extra == "doc"
Requires-Dist: sphinx-design==0.6.1 ; extra == "doc"
Requires-Dist: matplotlib==3.10.7 ; extra == "doc"
Requires-Dist: pytest==9.0.1 ; extra == "tests"
Requires-Dist: pytest-cov==7.0.0 ; extra == "tests"
Requires-Dist: requests==2.32.5 ; extra == "tests"
Project-URL: Discussions, https://github.com/ansys/pyrocky/discussions
Project-URL: Documentation, https://rocky.docs.pyansys.com
Project-URL: Issues, https://github.com/ansys/pyrocky/
Project-URL: Releases, https://github.com/ansys/pyrocky/releases
Project-URL: Source, https://github.com/ansys/pyrocky
Provides-Extra: doc
Provides-Extra: tests
